massivetools/Timer.py
massivetools/__init__.py
massivetools/anno_formater.py
massivetools/db_control.py
massivetools/loader.py
massivetools/logger.py
massivetools/preprocessor.py
massivetools/saver.py
massivetools/slack_api.py
massivetools/type_converter.py
massivetools/utils.py
massivetools/video_processor.py
massivetools/visualize.py
massivetools/mimdet/__init__.py
massivetools/mimsegment/__init__.py
massivetools/mimsegment/utils.py
massivetools/misc/__init__.py
massivetools/misc/coco2fiftyone.py
massivetools/misc/merge_coco.py
massivetools/monitoring/__init__.py
massivetools/monitoring/is_on.py
massivetools/tests/__init__.py
massivetools/tests/test_loader.py
massivetools/tests/test_utils.py
massivetools-0.0.2.dist-info/METADATA
massivetools-0.0.2.dist-info/WHEEL
massivetools-0.0.2.dist-info/top_level.txt
massivetools-0.0.2.dist-info/RECORD
